GnuplotPy3/GnuplotPy3.py
GnuplotPy3/__init__.py
GnuplotPy3-0.0.3.dist-info/LICENSE
GnuplotPy3-0.0.3.dist-info/METADATA
GnuplotPy3-0.0.3.dist-info/WHEEL
GnuplotPy3-0.0.3.dist-info/top_level.txt
GnuplotPy3-0.0.3.dist-info/RECORD
