Metadata-Version: 2.1
Name: GnuplotPy3
Version: 0.0.3
Summary: A minimal Python wrapper for Gnuplot.
Home-page: https://github.com/carbonscott/GnuplotPy3
Author: Cong Wang
Author-email: wangimagine@gmail.com
License: UNKNOWN
Keywords: Gnuplot,wrapper
Platform: UNKNOWN
Classifier: Programming Language :: Python :: 3
Classifier: License :: OSI Approved :: MIT License
Classifier: Operating System :: OS Independent
Requires-Python: >=3.6
